tortoise_vector/README.md
tortoise_vector/__init__.py
tortoise_vector/expression.py
tortoise_vector/field.py
tortoise_vector/py.typed
tortoise_vector-0.2.0.dist-info/METADATA
tortoise_vector-0.2.0.dist-info/WHEEL
tortoise_vector-0.2.0.dist-info/RECORD
