Metadata-Version: 2.3
Name: tortoise-vector
Version: 0.2.0
Summary: pgvector implementation for Tortoise-ORM
License: MIT
Author: Sebastien Nicolet
Author-email: snicolet95@gmail.com
Requires-Python: >=3.10
Classifier: License :: OSI Approved :: MIT License
Classifier: Programming Language :: Python :: 3
Classifier: Programming Language :: Python :: 3.10
Classifier: Programming Language :: Python :: 3.11
Classifier: Programming Language :: Python :: 3.12
Classifier: Programming Language :: Python :: 3.13
Requires-Dist: tortoise-orm[asyncpg] (>=0.23)
Project-URL: Documentation, https://github.com/Chr0nos/tortoise_vector/blob/master/tortoise_vector/README.md
Project-URL: Homepage, https://github.com/Chr0nos/tortoise_vector
Project-URL: Repository, https://github.com/Chr0nos/tortoise_vector.git
